{
	"name": "Questing v0.5.2
From Start to the beginning of Celadon
How to:
- You should be able to start the script from anywhere between Start and SSAnne
- When NidoranM is catched at route 22, login and put it in position #1
- Buy as many pokeballs as you can at the same time so you don't miss any shiny
- Use the moon stone on Nidorino when you get it at Mt.Moon (the bot will stop)
- If you use another pokemon as #1 instead of Nidoran M/Nidorino/Nidoking after Viridian City, the bot will use it instead and ignore the moon stone stop
- If the bot stops in a Pokemart, you need to buy pokeballs
Behaviour of the script:
- Pick Charmander
- Catch NidoranM route 22
- Wait for you to switch
- [HUMAN ACTION]
- Farm route 22 until NidoranM is 14
- Farm route 2 after the forest until NidoranM is 16
- Fight Brock
- Pick the moon stone
- If Nidorino is #1, waits for you to evolve Nidorino
- [HUMAN ACTION]
- Farm to the MtMoon until Nidoking is 28
- Pick the Helix fossil
- Farm to the Route 24 until Nidoking is 38
- Talk to Bill (and always do that once to check if it's already done)
- Fight Misty
- Fight the Team Rocket guy
- Goes in the stupidly written vision
- Talk to Surge
- Enter SSAnne and pass the identification room
- Pick the berry
- Fight Jackso
- Talk to all NPCs required to reach the Captain
- Get the HM01
- Wait in front of the arena for you to defeat it
- [HUMAN ACTION]
- Go look for the HM05 and catch pokemons if needed
- Go back to Cerulean and take the Rock Tunnel
- Go from Lavender to Celadon
- [The End, currently waiting for a new version of the bot]
Bugs:
- When leveling in route 24 the bot can end up in an infinity loop trying to run away constantly: log out
Report bugs to: https://proshine-bot.ml/viewtopic.php?pid=491
Contributors: c0pper",
	"author": "g0ld",
	"path": [
		{
			"condition": ["all",
				["any",
					["map", "Start"],
					["map", "Player Bedroom Pallet"],
					["map", "Player House Pallet"],
					["map", "Pallet Town"],
					["map", "Oaks Lab"]
				],
				["!hasItem", "Boulder Badge"]
			],
			"actions": [
				{
					"condition": ["map", "Start"],
					"actions": [
						{
							"condition": ["isNpcOnCell", [21,38]],
							"action": ["talkToNpcOnCell", [21,38]]
						},
						{
							"action": ["moveToCell", [26,87]]
						}
					]
				},
				{
					"condition": ["teamSize", "=", 0],
					"actions": [
						{
							"condition": ["map", "Player Bedroom Pallet"],
							"action": ["moveToMap", "Player House Pallet"]
						},
						{
							"condition": ["map", "Player House Pallet"],
							"action": ["moveToMap", "Link"]
						},
						{
							"condition": ["map", "Pallet Town"],
							"action": ["moveToMap", "Oaks Lab"]
						},
						{
							"condition": ["map", "Oaks Lab"],
							"actions": [
								{
									"condition": ["!isset", "OAK"],
									"action": ["talkToNpcOnCell", [7,4]],
								},
								{
									"action": ["talkToNpcOnCell", [10,6]],
								}
							]
						}
					]
				},
				{
					"condition": ["all",
						["teamSize", ">", 0],
						["!hasItem", "Pokeball"]
					],
					"actions": [
						{
							"condition": ["map", "Oaks Lab"],
							"actions": [
								{
									"condition": ["!hasItem", "Pokedex"],
									"action": ["talkToNpcOnCell", [7,4]],
								},
								{
									"action": ["moveToMap", "Link"],
								}
							]
						},
						{
							"condition": ["map", "Pallet Town"],
							"action": ["moveToMap", "Player House Pallet"]
						},
						{
							"condition": ["map", "Player House Pallet"],
							"actions": [
								{
									"condition": ["!isset", "MOM"],
									"action": ["talkToNpcOnCell", [7,6]]
								},
								{
									"action": ["moveToMap", "Player Bedroom Pallet"],
								}
							]
						},
						{
							"condition": ["map", "Player Bedroom Pallet"],
							"actions": [
								{
									"condition": ["isNpcOnCell", [7,3]],
									"action": ["talkToNpcOnCell", [7,3]]
								},
								{
									"condition": ["isNpcOnCell", [6,3]],
									"action": ["talkToNpcOnCell", [6,3]]
								}
							]
						}
					]
				},
				{
					"condition": ["hasItem", "Pokeball"],
					"actions": [
						{
							"condition": ["map", "Player Bedroom Pallet"],
							"action": ["moveToMap", "Player House Pallet"]
						},
						{
							"condition": ["map", "Player House Pallet"],
							"action": ["moveToMap", "Link"]
						},
						{
							"condition": ["map", "Pallet Town"],
							"actions": [
								{
									"condition": ["npcExists", "#133"],
									"action": ["talkToNpc", "#133"]
								},
								{
									"condition": ["npcExists", "Jackson"],
									"action": ["talkToNpc", "Jackson"]
								},
								{
									"action": ["moveToMap", "Route 1"]
								}
							]
						}
					]
				}
			]
		},

		{
			"condition": ["map", "Route 1"],
			"action": ["moveToMap", "Route 1 Stop House"]
		},
		{
			"condition": ["map", "Route 1 Stop House"],
			"action": ["moveToMap", "Viridian City"]
		},

		{
			"condition": ["map", "Viridian City"],
			"actions": [
				{
					"condition": ["isSet", "Viridian Jackson defeated"],
					"action": ["moveToMap", "Route 2"]
				},
				{
					"condition": ["!isSet", "Viridian Jackson checked"],
					"action": ["moveToMap", "Viridian City School"]
				},
				{
					"condition": ["!isSet", "Pokecenter Viridian"],
					"action": ["moveToMap", "Pokecenter Viridian"]
				},
				{
					"condition": ["any",
							["isPokemon1Usable", "=", false],
							["all",
								["teamSize", ">=", 2],
								["isPokemon2Usable", "=", false]
							]
					],
					"action": ["moveToMap", "Pokecenter Viridian"]
				},
				{
					"condition": ["all",
						["!isSet", "hasNidoranM"],
						["!hasItem", "Pokeball"]
					],
					"action": ["moveToMap", "Viridian Pokemart"]
				},
				{
					"condition": ["!isSet", "hasNidoranM"],
					"action": ["moveToMap", "Route 22"]
				},
				{
					"condition": ["!isSet", "NidoranM ready for Viridian Jackson"],
					"action": ["moveToMap", "Route 22"]
				},
				{
					"condition": ["!isSet", "Viridian Jackson defeated"],
					"action": ["moveToMap", "Viridian City School"]
				}
			]
		},

		{
			"condition": ["map", "Viridian City School"],
			"actions": [
				{
					"condition": ["isSet", "Viridian Jackson defeated"],
					"action": ["moveToMap", "Viridian City"]
				},
				{
					"condition": ["!isSet", "Viridian Jackson checked"],
					"action": ["moveToMap", "Viridian City School Underground"]
				},
				{
					"condition": ["!isSet", "NidoranM ready for Viridian Jackson"],
					"action": ["moveToMap", "Viridian City"],
				},
				{
					"action": ["moveToMap", "Viridian City School Underground"]
				}
			]
		},

		{
			"condition": ["map", "Viridian City School Underground"],
			"actions": [
				{
					"condition": ["isSet", "Viridian Jackson defeated"],
					"action": ["moveToMap", "Viridian City School"]
				},
				{
					"condition": ["all",
						["any",
							["isSet", "NidoranM ready for Viridian Jackson"],
							["!isSet", "Viridian Jackson checked"]
						],
						["isNpcOnCell", [7, 6]]
					],
					"action": ["talkToNpcOnCell", [7, 6]]
				},
				{
					"condition": ["isSet", "NidoranM ready for Viridian Jackson"],
					"action": ["talkToNpc", "Jackson"]
				},
				{
					"condition": ["!isSet", "NidoranM ready for Viridian Jackson"],
					"action": ["moveToMap", "Viridian City School"],
					"set": "Viridian Jackson checked"
				}
			]
		},

		{
			"condition": ["map", "Pokecenter Viridian"],
			"actions": [
				{
					"condition": ["any",
						["isPokemon1Usable", "=", false],
						["all",
							["teamSize", ">=", 2],
							["isPokemon2Usable", "=", false]
						]
					],
					"action": ["usePokecenter"],
				},
				{
					"action": ["moveToMap", "Viridian City"],
				},
			],
			"set": "Pokecenter Viridian"
		},

		{
			"condition": ["all",
				["map", "Viridian Pokemart"],
				["!isSet", "hasNidoranM"],
				["hasItem", "Pokeball"]
			],
			"action": ["moveToMap", "Viridian City"],
			"set": "Waiting for you to buy pokeballs [HUMAN ACTION]"
		},

		{
			"condition": ["map", "Route 22"],
			"actions": [
				{
					"condition": ["all",
						["isPokemon1Usable"],
						["any",
							["!isSet", "NidoranM ready for Viridian Jackson"],
							["!isSet", "hasNidoranM"],
						]
					],
					"action": ["moveToRectangle", [50, 11], [52, 20]]
				},
				{
					"action": ["moveToMap", "Viridian City"]
				}
			]
		},
		
		
		{
			"condition": ["all",
				["map", "Route 2"],
				["inRectangle", [0, 90], [24, 130]]
			],
			"action": ["moveToMap", "Route 2 Stop"]
		},

		{
			"condition": ["map", "Route 2 Stop"],
			"action": ["moveToMap", "Viridian Forest"]
		},
		{
			"condition": ["map", "Viridian Forest"],
			"action": ["moveToMap", "Route 2 Stop2"]
		},
		{
			"condition": ["map", "Route 2 Stop2"],
			"action": ["moveToMap", "Route 2"]
		},

		{
			"condition": ["all",
				["map", "Route 2"],
				["inRectangle", [0, 0], [28, 42]]
			],
			"actions": [
				{
					"condition": ["all",
						["!isSet", "First pokemon ready for Brock"],
						["isPokemon1Usable"],
						["isSet", "Pokecenter Pewter"]
					],
					"action": ["moveToRectangle", [19, 10], [21, 14]]
				},
				{
					"action": ["moveToMap", "Pewter City"]
				}
			]
		},

		{
			"condition": ["map", "Pewter City"],
			"actions": [
				{
					"condition": ["all",
						["cell", [23, 21]],
						["isNpcOnCell", [23, 22]]
					],
					"action": ["talkToNpcOnCell", [23, 22]]
				},
				{
					"condition": ["hasItem", "Boulder Badge"],
					"action": ["moveToMap", "Route 3"]
				},
				{
					"condition": ["any",
						["isPokemon1Usable", "=", false],
						["!isSet", "Pokecenter Pewter"]
					],
					"action": ["moveToMap", "Pokecenter Pewter"]
				},
				{
					"condition": ["!isSet", "First pokemon ready for Brock"],
					"action": ["moveToMap", "Route 2"]
				},
				{
					"action": ["moveToMap", "Pewter Gym"]
				}
			]
		},

		{
			"condition": ["map", "Pokecenter Pewter"],
			"actions": [
				{
					"condition": ["isPokemon1Usable", "=", false],
					"action": ["usePokecenter"],
				},
				{
					"action": ["moveToMap", "Pewter City"],
				}
			],
			"set": "Pokecenter Pewter"
		},

		{
			"condition": ["map", "Pewter Gym"],
			"actions": [
				{
					"condition": ["hasItem", "Boulder Badge"],
					"action": ["moveToMap", "Pewter City"]
				},
				{
					"action": ["talkToNpcOnCell", [7, 5]]
				}
			]
		},

		{
			"condition": ["map", "Route 3"],
			"actions": [
				{
					"condition": ["any",
						["isPokemon1Usable", "=", false],
						["!isSet", "Pokecenter Route 3"]
					],
					"action": ["moveToMap", "Pokecenter Route 3"]
				},
				{
					"condition": ["all",
						["hasItem", "Moon Stone"],
						["pokemon1", "=", "Nidorino"]
					],
					"action": ["moveToRectangle", [83, 17], [85, 22]],
					"set": "Waiting for you to evolve Nidorino to Nidoking [HUMAN ACTION]"
				},
				{
					"action": ["moveToMap", "Mt. Moon 1F"]
				}
			]
		},

		{
			"condition": ["map", "Pokecenter Route 3"],
			"actions": [
				{
					"condition": ["isPokemon1Usable", "=", false],
					"action": ["usePokecenter"],
				},
				{
					"action": ["moveToMap", "Route 3"],
				}
			],
			"set": "Pokecenter Route 3"
		},

		{
			"condition": ["map", "Mt. Moon 1F"],
			"actions": [
				{
					"condition": ["isPokemon1Usable", "=", false],
					"action": ["moveToMap", "Route 3"]
				},
				{
					"condition": ["all",
						["isSet", "First pokemon ready for Moon Stone"],
						["isNpcOnCell", [19, 16]],
						["pokemon1", "=", "Nidorino"]
					],
					"action": ["talkToNpcOnCell", [19, 16]]
				},
				{
					"condition": ["all",
						["hasItem", "Moon Stone"],
						["pokemon1", "=", "Nidorino"],
						["isSet", "First pokemon ready for Moon Stone"]
					],
					"action": ["moveToMap", "Route 3"],
					"set": "Waiting for you to evolve Nidorino to Nidoking [HUMAN ACTION]"
				},
				{
					"condition": ["!isSet", "First pokemon ready for Mt.Moon"],
					"action": ["moveToRectangle", [37, 60], [40, 62]]
				},
				{
					"action": ["moveToCell", [21, 20]]
				}
			]
		},

		{
			"condition": ["all",
				["map", "Mt. Moon B1F"],
				["inRectangle", [55, 14], [76, 35]]],
			"action": ["moveToCell", [56, 34]]
		},

		{
			"condition": ["all",
				["map", "Mt. Moon B2F"],
				["inRectangle", [10, 22], [63, 70]]
			],
			"actions": [
				{
					"condition": ["isNpcOnCell", [25, 29]],
					"actions": [
						{
							"condition": ["any",
								["all",
									["!isSet", "MtMoon go talk to fossil guy"],
									["!isSet", "MtMoon talked to fossil guy"]
								],
								["all",
									["isSet", "MtMoon go talk to fossil guy"],
									["isSet", "MtMoon talked to fossil guy"]
								]
							],
							"action": ["talkToNpcOnCell", [25, 29]]
						},
						{
							"action": ["talkToNpcOnCell", [23, 31]]
						}
					]
				},
				{
					"condition": ["isNpcOnCell", [26, 23]],
					"action": ["talkToNpcOnCell", [26, 23]]
				},
				{
					"action": ["moveToCell", [17, 27]]
				}
			]
		},

		{
			"condition": ["all",
			["map", "Mt. Moon B1F"],
			["inRectangle", [32, 19], [42, 22]]],
			"action": ["moveToCell", [41, 20]]
		},
		{
			"condition": ["map", "Mt. Moon Exit"],
			"action": ["moveToMap", "Route 4"]
		},
		{
			"condition": ["all",
				["map", "Route 4"],
				["cell", [91,21]]
			],
			"action": ["moveToMap", "Cerulean City"]
		},
		{
			"condition": ["map", "Route 4"],
			"action": ["moveToCell", [91,21]]
		},

		{
			"condition": ["map", "Cerulean City"],
			"actions": [
				{
					"condition": ["any",
						["isPokemon1Usable", "=", false],
						["!isSet", "Pokecenter Cerulean"]
					],
					"action": ["moveToMap", "Pokecenter Cerulean"]
				},
				{
					"condition": ["all",
						["hasItem", "Cascade Badge"],
						["isNpcOnCell", [47, 27]]
					],
					"action": ["talkToNpcOnCell", [47, 27]]
				},
				{
					"condition": ["all",
						["hasItem", "HM05 - FLash"],
						["!hasItem", "Rainbow Badge"]
					],
					"action": ["moveToMap", "Route 9"]
				},
				{
					"condition": ["hasItem", "Cascade Badge"],
					"action": ["moveToMap", "Route 5"]
				},
				{
					"condition": ["any",
						["!isSet", "First pokemon ready for Misty"],
						["!isSet", "Bill has book"]
					],
					"action": ["moveToCell", [39, 0]]
				},
				{
					"condition": ["all",
						["isSet", "Bill has book"],
						["!hasItem", "Cascade Badge"]
					],
					"action": ["moveToMap", "Cerulean Gym"]
				}
			]
		},

		{
			"condition": ["map", "Pokecenter Cerulean"],
			"actions": [
				{
					"condition": ["isPokemon1Usable", "=", false],
					"action": ["usePokecenter"],
				},
				{
					"action": ["moveToMap", "Cerulean City"],
				}
			],
			"set": "Pokecenter Cerulean"
		},

		{
			"condition": ["all",
				["map", "Route 24"],
				["inRectangle", [14, 1], [15, 30]]
			],
			"actions": [
				{
					"condition": ["all",
						["isPokemon1Usable"],
						["any",
							["!isSet", "First pokemon ready for Misty"],
							["!isSet", "Bill has book"]
						]
					],
					"action": ["moveToMap", "Route 25"]
				},
				{
					"action": ["moveToMap", "Cerulean City"]
				}
			]
		},

		{
			"condition": ["map", "Route 25"],
			"actions": [
				{
					"condition": ["all",
						["isPokemon1Usable"],
						["!isSet", "First pokemon ready for Misty"]
					],
					"action": ["moveToCell", [9, 30]]
				},
				{
					"condition": ["!isSet", "Bill has book"],
					"action": ["moveToMap", "Bills House"]
				},
				{
					"action": ["moveToCell", [14, 30]]
				}
			]
		},

		{
			"condition": ["all",
				["map", "Route 24"],
				["inRectangle", [6, 0], [9, 16]]
			],
			"actions": [
				{
					"condition": ["all",
						["!isSet", "First pokemon ready for Misty"],
						["isPokemon1Usable"]
					],
					"action": ["moveToRectangle", [7,2], [9, 2]]
				},
				{
					"action": ["moveToMap", "Route 25"]
				}
			]
		},

		{
			"condition": ["map", "Bills House"],
			"actions": [
				{
					"condition": ["!isSet", "Bill found book"],
					"action": ["talkToNpcOnCell", [18,2]]
				},
				{
					"condition": ["!isSet", "Bill has book"],
					"action": ["talkToNpc", "Bill"]
				},
				{
					"action": ["moveToMap", "Route 25"]
				}
			]
		},

		{
			"condition": ["map", "Cerulean Gym"],
			"actions": [
				{
					"condition": ["!hasItem", "Cascade Badge"],
					"action": ["talkToNpcOnCell", [10, 6]]
				},
				{
					"action": ["moveToMap", "Cerulean City"]
				}
			]
		},

		{
			"condition": ["map", "Route 9"],
			"actions": [
				{
					"condition": ["isNpcOnCell", [11,29]],
					"action": ["talkToNpcOnCell", [11,29]]
				},
				{
					"condition": ["isNpcOnCell", [24,13]],
					"action": ["talkToNpcOnCell", [24,13]]
				},
				{
					"condition": ["isNpcOnCell", [25,13]],
					"action": ["talkToNpcOnCell", [25,13]]
				},
				{
					"condition": ["isNpcOnCell", [26,13]],
					"action": ["talkToNpcOnCell", [26,13]]
				},
				{
					"condition": ["all",
						["hasItem", "HM05 - Flash"],
						["!hasItem", "Rainbow Badge"]
					],
					"action": ["moveToMap", "Route 10"]
				},
				{
					"action": ["moveToMap", "Cerulean City"]
				}
			]
		},

		{
			"condition": ["all",
				["map", "Route 10"],
				["inRectangle", [10,0], [22,8]]
			],
			"actions": [
				{
					"condition": ["all",
						["hasItem", "HM05 - Flash"],
						["!hasItem", "Rainbow Badge"]
					],
					"action": ["moveToMap", "Rock Tunnel 1"]
				},
				{
					"action": ["moveToMap", "Route 9"]
				}
			]
		},

		{
			"condition": ["all",
				["map", "Rock Tunnel 1"],
				["any",
					["inRectangle", [40, 8], [44, 10]],
					["inRectangle", [34, 8], [38, 9]],
					["inRectangle", [34, 8], [36, 16]],
				]
			],
			"action": ["moveToCell", [35, 16]]
		},
		{
			"condition": ["all",
				["map", "Rock Tunnel 2"],
				["any",
					["inRectangle", [6, 5], [26, 11]],
					["inRectangle", [27, 5], [45, 6]],
					["inRectangle", [36, 7], [45, 17]],
					["inRectangle", [36, 9], [37, 17]],
					["inRectangle", [38, 8], [45, 10]],
					["inRectangle", [37, 5], [45,  7]],
					["inRectangle", [35, 5], [37, 5]],
					["inRectangle", [29, 7], [26, 9]],
					["inRectangle", [29, 5], [35, 6]],
					["inRectangle", [29, 5], [29, 6]],
					["inRectangle", [26, 6], [29, 6 ]],
					["inRectangle", [26, 6], [26,9]],
					["inRectangle", [18, 9], [26, 9]],
					["inRectangle", [15, 10], [18, 9]],
					["inRectangle", [13, 9], [15, 10]],
					["inRectangle", [11, 8], [12, 10]],
					["inRectangle", [9, 8], [11, 8]],
					["inRectangle", [8, 6], [9, 8]],
					["inRectangle", [6, 5], [8, 6]]
				]
			],
			"action": ["moveToCell", [7, 5]]
		},
		{
			"condition": ["all",
				["map", "Rock Tunnel 1"],
				["any",
					["inRectangle", [6, 6], [10, 9]],
					["inRectangle", [10, 7], [12,8]],
					["inRectangle",[12, 5], [16, 8]],
					["inRectangle", [17, 8], [20, 8]],
					["inRectangle", [20, 8], [23, 9]],
					["inRectangle", [23, 9], [23, 13]],
					["inRectangle", [6, 13], [23, 14]],
					["inRectangle", [6, 13], [9, 16]]
				]
			],
			"action": ["moveToCell", [8, 15]]
		},
		{
			"condition": ["all",
				["map", "Rock Tunnel 2"],
				["any",
					["inRectangle", [6, 17], [26, 27]],
					["inRectangle", [9, 13], [26, 21]],
					["inRectangle", [12, 21], [26, 22]],
					["inRectangle", [9, 22], [12, 22]],
					["inRectangle", [9, 13], [26, 21]],
					["inRectangle", [9, 22], [10, 27]],
					["inRectangle", [7, 25], [10, 27]]
				]
			],
			"action": ["moveToCell", [8, 26]]
		},
		{
			"condition": ["all",
				["map", "Rock Tunnel 1"],
				["any",
					["inRectangle", [6, 28], [9, 31]],
					["inRectangle", [8, 27], [9, 31]],
					["inRectangle", [8, 27], [22, 32]]
				]
			],
			"action": ["moveToMap", "Route 10"]
		},
		{
			"condition": ["all",
				["map", "Route 10"],
				["inRectangle", [2, 44], [7, 47]],
			],
			"action": ["moveToMap", "Lavender Town"]
		},
		{
			"condition": ["map", "Lavender Town"],
			"action": ["moveToMap", "Route 8"]
		},
		{
			"condition": ["map", "Route 8"],
			"action": ["moveToMap", "Underground House 4"]
		},
		{
			"condition": ["map", "Underground House 4"],
			"action": ["moveToMap", "Underground1"]
		},
		{
			"condition": ["map", "Underground1"],
			"action": ["moveToMap", "Underground House 3"]
		},
		{
			"condition": ["map", "Underground House 3"],
			"action": ["moveToMap", "Route 7"]
		},
		{
			"condition": ["map", "Route 7"],
			"action": ["moveToMap", "Celadon City"]
		},
		{
			"condition": ["map", "Celadon City"],
			"action": ["moveToMap", "Celadon Gamecorner Stairs"]
		},
		{
			"condition": ["map", "Celadon Gamecorner Stairs"],
			"action": ["moveToMap", "Rocket Hideout B1F"]
		},

		{
			"condition": ["map", "Route 5"],
			"actions": [
				{
					"condition": ["all",
						["hasItem", "HM05 - Flash"],
						["!hasItem", "Rainbow Badge"]
					],
					"action": ["moveToMap", "Cerulean City"]
				},
				{
					"action": ["moveToMap", "Underground House 1"]
				}
			]
		},
		{
			"condition": ["map", "Underground House 1"],
			"actions": [
				{
					"condition": ["all",
						["hasItem", "HM05 - Flash"],
						["!hasItem", "Rainbow Badge"]
					],
					"action": ["moveToMap", "Route 5"]
				},
				{
					"action": ["moveToMap", "Underground2"]
				}
			]
		},
		{
			"condition": ["map", "Underground2"],
			"actions": [
				{
					"condition": ["all",
						["hasItem", "HM05 - Flash"],
						["!hasItem", "Rainbow Badge"]
					],
					"action": ["moveToMap", "Underground House 1"]
				},
				{
					"action": ["moveToMap", "Underground House 2"]
				}
			]
		},
		{
			"condition": ["map", "Underground House 2"],
			"actions": [
				{
					"condition": ["all",
						["hasItem", "HM05 - Flash"],
						["!hasItem", "Rainbow Badge"]
					],
					"action": ["moveToMap", "Underground2"]
				},
				{
					"action": ["moveToMap", "Route 6"]
				}
			]
		},


		{
			"condition": ["map", "Route 6"],
			"actions": [
				{
					"condition": ["isPokemon1Usable", "=", false],
					"action": ["moveToMap", "Vermilion City"]
				},
				{
					"condition": ["all",
						["isNpcOnCell", [24, 54]],
						["!isSet", "Psychic Wade explained"]
					],
					"action": ["talkToNpcOnCell", [24, 54]]
				},
				{
					"condition": ["all",
						["isNpcOnCell", [24, 54]],
						["isSet", "Surge talked"],
						["!isSet", "Psychic Wade congrated"]
					],
					"action": ["talkToNpcOnCell", [24, 54]]
				},
				{
					"condition": ["all",
						["isSet", "Surge talked"],
						["!isSet", "Psychic Wade congrated"]
					],
					"action": ["moveToMap", "Vermilion City"],
					"set": "Surge talked",
					"set": "Psychic Wade congrated"
				},
				{
					"condition": ["all",
						["hasItem", "HM01 - Cut"],
						["!isSet", "First pokemon ready for Surge"]
					],
					"action": ["moveToRectangle", [24,47], [28,53]]
				},
				{
					"condition": ["!hasItem", "HM05 - Flash"],
					"action": ["moveToMap", "Vermilion City"]
				},
				{
					"action": ["moveToMap", "Underground House 2"]
				}
			]
		},

		{
			"condition": ["map", "Vermilion City 2"],
			"action": ["talkToNpcOnCell", [44, 30]]
		},

		{
			"condition": ["map", "Pokecenter Vermilion"],
			"actions": [
				{
					"condition": ["isPokemon1Usable", "=", false],
					"action": ["usePokecenter"],
				},
				{
					"action": ["moveToMap", "Vermilion City"],
				}
			],
			"set": "Pokecenter Vermilion"
		},

		{
			"condition": ["map", "Vermilion City"],
			"actions": [
				{
					"condition": ["any",
						["isPokemon1Usable", "=", false],
						["!isSet", "Pokecenter Vermilion"]
					],
					"action": ["moveToMap", "Pokecenter Vermilion"]
				},
				{
					"condition": ["all",
						["!isSet", "Psychic Wade explained"],
						["isNpcOnCell", [38, 63]]
					],
					"action": ["moveToMap", "Route 6"]
				},
				{
					"condition": ["all",
						["isSet", "Psychic Wade explained"],
						["isNpcOnCell", [38, 63]]
					],
					"action": ["talkToNpcOnCell", [38, 63]]
				},
				{
					"condition": ["!isSet", "Psychic Wade congrated"],
					"action": ["moveToMap", "Route 6"],
					"set": "Surge talked"
				},
				{
					"condition": ["!hasItem", "HM01 - Cut"],
					"action": ["moveToCell", [40, 67]]
				},
				{
					"condition": ["all",
						["!hasItem", "Thunder Badge"],
						["!isSet", "First pokemon ready for Surge"]
					],
					"action": ["moveToMap", "Route 6"]
				},
				{
					"condition": ["!hasItem", "Thunder Badge"],
					"action": ["moveToRectangle", [30, 45], [34, 48]],
					"set": "Waiting for you to use cut and go through the tree [HUMAN ACTION]",
					"set": "The End"
				},
				{
					"condition": ["any",
						["!isSet", "First pokemon does not need digglet cave"],
						["all",
							["!hasItem", "HM05 - Flash"],
							["any",
								["hasItem", "Pokeball"],
								["hasItem", "Great Ball"],
								["hasItem", "Ultra Ball"]
							]
						]
					],
					"action": ["moveToMap", "Route 11"]
				},
				{
					"condition": ["all",
						["all",
							["!hasItem", "Pokeball"],
							["!hasItem", "Great Ball"],
							["!hasItem", "Ultra Ball"]
						],
						["!hasItem", "HM05 - Flash"]
					],
					"action": ["moveToMap", "Vermilion Pokemart"]
				},
				{
					"condition": ["all",
						["hasItem", "HM05 - Flash"],
						["!hasItem", "Poke Flute"]
					],
					"action": ["moveToMap", "Route 6"]
				}
			]
		},

		{
			"condition": ["map", "Vermilion Pokemart"],
			"actions": [
				{
					"condition": ["all",
						["all",
							["!hasItem", "Pokeball"],
							["!hasItem", "Great Ball"],
							["!hasItem", "Ultra Ball"]
						],
						["!hasItem", "HM05 - Flash"]
					],
					"action": ["moveToRectangle", [0,0], [5000, 5000]],
					"set": "Wait for you to buy pokeballs in case the HM05 needs them [HUMAN ACTION]"
				},
				{
					"action": ["moveToMap", "Vermilion City"]
				}
			]
		},

		{
			"condition": ["all",
				["map", "SSAnne 1F"],
				["hasItem", "HM01 - Cut"]
			],
			"action": ["moveToMap", "Vermilion City"]
		},
		{
			"condition": ["all",
				["map", "SSAnne 1F"],
				["!isSet", "Usher Dale talked"]
			],
			"action": ["talkToNpc", "Usher Dale"]
		},
		{
			"condition": ["all",
				["map", "SSAnne 1F"],
				["!isSet", "SSAnne Doctor Neumann has Pecha Berry"]
			],
			"action": ["moveToMap", "SSAnne 1F Kitchen"]
		},

		{
			"condition": ["all",
				["map", "SSAnne 1F Kitchen"],
				["!isSet", "SSAnne Doctor Neumann has Pecha Berry"]
			],
			"actions": [
				{
					"condition": ["!hasItem", "Pecha Berry"],
					"action": ["talkToNpcOnCell", [14, 9]]
				},
				{
					"action": ["talkToNpc", "Doctor Neumann"]
				}
			]
		},
		{
			"condition": ["map", "SSAnne 1F Kitchen"],
			"action": ["moveToMap", "SSAnne 1F"]
		},

		{
			"condition": ["all",
				["map", "SSAnne Basement Room5"],
				["npcExists", "Usher Dale"]
			],
			"actions": [
				{
					"condition": ["!isSet", "SSAnne Basement PC checked"],
					"action": ["talkToNpcOnCell", [6, 3]]
				},
				{
					"condition": ["isSet", "SSAnne Basement PC checked"],
					"action": ["talkToNpc", "Usher Dale"]
				}
			]
		},
		{
			"condition": ["map", "SSAnne Basement Room5"],
			"action": ["moveToMap", "SSAnne Basement"]
		},
		{
			"condition": ["map", "SSAnne Basement"],
			"action": ["moveToMap", "SSAnne 1F"]
		},
		{
			"condition": ["all",
				["map", "SSAnne 1F"],
				["isSet", "Usher Dale talked"]
			],
			"action": ["moveToMap", "SSAnne 2F"]
		},

		{
			"condition": ["all",
				["map", "SSAnne 2F"],
				["!isSet", "SSAnne Jackson defeated"]
			],
			"action": ["moveToMap", "SSAnne 3F"]
		},
		{
			"condition": ["all",
				["map", "SSAnne 2F"],
				["isNpcOnCell", [26, 4]]
			],
			"actions": [
				{
					"condition": ["!isSet", "SSAnne Doctor Neumann has Pecha Berry"],
					"action": ["moveToMap", "SSAnne 1F"]
				},
				{
					"condition": ["!isSet", "SSAnne Jenson has Pecha Berry"],
					"action": ["moveToMap", "SSAnne 2F Room6"]
				},
				{
					"condition": ["!isSet", "SSAnne Talked to Blissey"],
					"action": ["moveToMap", "SSAnne 3F"]
				},
				{
					"action": ["talkToNpcOnCell", [26, 4]]
				}
			],
		},
		{
			"condition": ["all",
				["map", "SSAnne 2F"],
				["!hasItem", "HM01 - Cut"]
			],
			"action": ["moveToMap", "SSAnne 2F Captain Room"]
		},
		{
			"condition": ["map", "SSAnne 2F"],
			"action": ["moveToMap", "SSAnne 1F"]
		},

		{
			"condition": ["all",
				["map", "SSAnne 2F Captain Room"],
				["!hasItem", "HM01 - Cut"]
			],
			"action": ["talkToNpc", "Captain"]
		},
		{
			"condition": ["map", "SSAnne 2F Captain Room"],
			"action": ["moveToMap", "SSAnne 2F"]
		},

		{
			"condition": ["all",
				["map", "SSAnne 2F Room6"],
				["!isSet", "SSAnne Jenson has Pecha Berry"]
			],
			"action": ["talkToNpc", "Jenson"]
		},
		{
			"condition": ["map", "SSAnne 2F Room6"],
			"action": ["moveToMap", "SSAnne 2F"]
		},

		{
			"condition": ["all",
				["map", "SSAnne 3F"],
				["!isSet", "SSAnne Jackson defeated"]
			],
			"action": ["moveToMap", "SSAnne 3F Battle Room"]
		},
		{
			"condition": ["all",
				["map", "SSAnne 3F"],
				["isSet", "SSAnne Jenson has Pecha Berry"],
				["!isSet", "SSAnne Talked to Blissey"]
			],
			"action": ["moveToMap", "Ballroom SS Anne"]
		},
		{
			"condition": ["map", "SSAnne 3F"],
			"action": ["moveToMap", "SSAnne 2F"]
		},

		{
			"condition": ["all",
				["map", "Ballroom SS Anne"],
				["npcExists", "#242"],
				["!isSet", "SSAnne Talked to Blissey"]
			],
			"action": ["talkToNpc", "#242"]
		},
		{
			"condition": ["map", "Ballroom SS Anne"],
			"action": ["moveToMap", "SSAnne 3F"],
			"set": "SSAnne Talked to Blissey"
		},

		{
			"condition": ["all",
				["map", "SSAnne 3F Battle Room"],
				["isNpcOnCell", [8,5]]
			],
			"action": ["talkToNpc", "Jackson"]
		},
		{
			"condition": ["map", "SSAnne 3F Battle Room"],
			"action": ["moveToMap", "SSAnne 3F"],
			"set": "SSAnne Jackson defeated"
		},

		{
			"condition": ["map", "Route 11"],
			"actions": [
				{
					"condition": ["isNpcOnCell", [10, 13]],
					"action": ["talkToNpcOnCell", [10, 13]]
				},
				{
					"condition": ["all",
						["isPokemon1Usable"],
						["!hasItem", "HM05 - Flash"],
						["isSet", "Remember to unset 'Oak's Aide wants more pokemons'"],
						["isSet", "Oak's Aide wants more pokemons"]
					],
					"action": ["moveToMap", "Digletts Cave Entrance 2"],
					"set": "to get pass the buggy assert",
					"unset": "Oak's Aide wants more pokemons"
				},
				{
					"condition": ["all",
						["isPokemon1Usable"],
						["!hasItem", "HM05 - Flash"],
						["isSet", "Remember to unset 'Oak's Aide wants more pokemons'"]
					],
					"action": ["moveToMap", "Digletts Cave Entrance 2"],
					"set": "to get pass the buggy assert",
					"unset": "Remember to unset 'Oak's Aide wants more pokemons'",
				},
				{
					"condition": ["all",
						["isSet", "Oak's Aide wants more pokemons"],
						["isPokemon1Usable"],
						["any",
							["hasItem", "Pokeball"],
							["hasItem", "Great Ball"],
							["hasItem", "Ultra Ball"]
						]
					],
					"action": ["moveToGrass"]
				},
				{
					"condition": ["all",
						["isPokemon1Usable"],
						["any",
							["!isSet", "First pokemon does not need digglet cave"],
							["all",
								["!hasItem", "HM05 - Flash"],
								["any",
									["hasItem", "Pokeball"],
									["hasItem", "Great Ball"],
									["hasItem", "Ultra Ball"]
								]
							]
						]
					],
					"action": ["moveToMap", "Digletts Cave Entrance 2"]
				},
				{
					"action": ["moveToMap", "Vermilion City"]
				}
			]
		},

		{
			"condition": ["map", "Digletts Cave Entrance 2"],
			"actions": [
				{
					"condition": ["all",
						["isPokemon1Usable"],
						["!hasItem", "HM05 - Flash"],
						["isSet", "Remember to unset 'Oak's Aide wants more pokemons'"],
						["isSet", "Oak's Aide wants more pokemons"]
					],
					"action": ["moveToMap", "Digletts Cave"],
					"set": "to get pass the buggy assert",
					"unset": "Oak's Aide wants more pokemons"
				},
				{
					"condition": ["all",
						["isPokemon1Usable"],
						["!hasItem", "HM05 - Flash"],
						["isSet", "Remember to unset 'Oak's Aide wants more pokemons'"]
					],
					"action": ["moveToMap", "Digletts Cave"],
					"set": "to get pass the buggy assert",
					"unset": "Remember to unset 'Oak's Aide wants more pokemons'",
				},
				{
					"condition": ["all",
						["!isSet", "First pokemon does not need digglet cave"],
						["isPokemon1Usable"],
						["!isSet", "Oak's Aide wants more pokemons"]
					],
					"action": ["moveToRectangle", [17, 25], [24, 26]]
				},
				{
					"condition": ["all",
						["isPokemon1Usable"],
						["all",
							["!hasItem", "HM05 - Flash"],
							["any",
								["hasItem", "Pokeball"],
								["hasItem", "Great Ball"],
								["hasItem", "Ultra Ball"]
							]
						],
						["!isSet", "Oak's Aide wants more pokemons"]
					],
					"action": ["moveToMap", "Digletts Cave"]
				},
				{
					"action": ["moveToMap", "Route 11"]
				}
			]
		},

		{
			"condition": ["map", "Digletts Cave"],
			"actions": [
				{
					"condition": ["all",
						["isPokemon1Usable"],
						["!hasItem", "HM05 - Flash"],
						["isSet", "Remember to unset 'Oak's Aide wants more pokemons'"],
						["isSet", "Oak's Aide wants more pokemons"]
					],
					"action": ["moveToMap", "Digletts Cave Entrance 1"],
					"set": "to get pass the buggy assert",
					"unset": "Oak's Aide wants more pokemons"
				},
				{
					"condition": ["all",
						["isPokemon1Usable"],
						["!hasItem", "HM05 - Flash"],
						["isSet", "Remember to unset 'Oak's Aide wants more pokemons'"]
					],
					"action": ["moveToMap", "Digletts Cave Entrance 1"],
					"set": "to get pass the buggy assert",
					"unset": "Remember to unset 'Oak's Aide wants more pokemons'",
				},
				{
					"condition": ["all",
						["isPokemon1Usable"],
						["!hasItem", "HM05 - Flash"],
						["any",
							["hasItem", "Pokeball"],
							["hasItem", "Great Ball"],
							["hasItem", "Ultra Ball"]
						],
						["!isSet", "Oak's Aide wants more pokemons"]
					],
					"action": ["moveToMap", "Digletts Cave Entrance 1"],
				},
				{
					"action": ["moveToMap", "Digletts Cave Entrance 2"],
				}
			]
		},

		{
			"condition": ["map", "Digletts Cave Entrance 1"],
			"actions": [
				{
					"condition": ["all",
						["any",
							["hasItem", "Pokeball"],
							["hasItem", "Great Ball"],
							["hasItem", "Ultra Ball"]
						],
						["!isSet", "hasPokeballs"]
					],
					"action": ["moveToRectangle", [12,24], [18,27]],
					"set": "hasPokeballs"
				},
				{
					"condition": ["all",
						["all",
							["!hasItem", "Pokeball"],
							["!hasItem", "Great Ball"],
							["!hasItem", "Ultra Ball"]
						],
						["isSet", "hasPokeballs"]
					],
					"action": ["moveToMap", "Digletts Cave"],
					"set": "placeholder",
					"unset": "hasPokeballs"
				},
				{
					"condition": ["all",
						["isPokemon1Usable"],
						["!hasItem", "HM05 - Flash"],
						["isSet", "Remember to unset 'Oak's Aide wants more pokemons'"],
						["isSet", "Oak's Aide wants more pokemons"]
					],
					"action": ["moveToMap", "Route 2"],
					"set": "to get pass the buggy assert",
					"unset": "Oak's Aide wants more pokemons"
				},
				{
					"condition": ["all",
						["isPokemon1Usable"],
						["!hasItem", "HM05 - Flash"],
						["isSet", "Remember to unset 'Oak's Aide wants more pokemons'"]
					],
					"action": ["moveToMap", "Route 2"],
					"set": "to get pass the buggy assert",
					"unset": "Remember to unset 'Oak's Aide wants more pokemons'",
				},
				{
					"condition": ["all",
						["isPokemon1Usable"],
						["!hasItem", "HM05 - Flash"],
						["any",
							["hasItem", "Pokeball"],
							["hasItem", "Great Ball"],
							["hasItem", "Ultra Ball"]
						],
						["isSet", "Oak's Aide wants more pokemons"]
					],
					"action": ["moveToMap", "Digletts Cave"]
				},
				{
					"condition": ["all",
						["isPokemon1Usable"],
						["!hasItem", "HM05 - Flash"],
						["any",
							["hasItem", "Pokeball"],
							["hasItem", "Great Ball"],
							["hasItem", "Ultra Ball"]
						]
					],
					"action": ["moveToMap", "Route 2"]
				},
				{
					"action": ["moveToMap", "Digletts Cave"]
				}
			]
		},

		{
			"condition": ["all",
				["map", "Route 2"],
				["inRectangle", [29,31], [42,90]]
			],
			"actions": [
				{
					"condition": ["all",
						["isPokemon1Usable"],
						["!isSet", "Oak's Aide wants more pokemons"],
						["!hasItem", "HM05 - Flash"],
						["any",
							["hasItem", "Pokeball"],
							["hasItem", "Great Ball"],
							["hasItem", "Ultra Ball"]
						]
					],
					"action": ["moveToMap", "Route 2 Stop3"]
				},
				{
					"action": ["moveToMap", "Digletts Cave Entrance 1"]
				}
			]
		},

		{
			"condition": ["map", "Route 2 Stop3"],
			"actions": [
				{
					"condition": ["all",
						["isPokemon1Usable"],
						["!hasItem", "HM05 - Flash"],
						["!isSet", "Oak's Aide wants more pokemons"],
						["any",
							["hasItem", "Pokeball"],
							["hasItem", "Great Ball"],
							["hasItem", "Ultra Ball"]
						]
					],
					"action": ["talkToNpc", "Oak's Aide"]
				},
				{
					"action": ["moveToMap", "Route 2"]
				}
			]
		}

	],
	"battle": [
		{
			"condition": ["isOpponentShiny"],
			"action": ["useItem", "Ultra Ball", "Great Ball", "Pokeball"]
		},
		{
			"condition": ["all",
				["isSet", "Oak's Aide wants more pokemons"],
				["alreadyCaught", "=", false],
				["isSet", "hasPokeballs"]
			],
			"action": ["useItem", "Ultra Ball", "Great Ball", "Pokeball"],
			"set": "Remember to unset 'Oak's Aide wants more pokemons'",
		},
		{
			"condition": ["all",
				["opponentPokemon", "Nidoran M"],
				["alreadyCaught", "=", false]
			],
			"action": ["useItem", "Ultra Ball", "Great Ball", "Pokeball"]
		},
		{
			"condition": ["all",
				["any",
					["activePokemon", "Nidoran M"],
					["activePokemon", "Nidorino"],
					["activePokemon", "Nidoking"]
				],
				["!isSet", "hasNidoranM"]
			],
			"action": ["attack"],
			"set": "hasNidoranM"
		},
		{
			"condition": ["all",
				["activePokemon", "Nidoran M"],
				["activeLevel", "<=", 6],
				["isPokemon2Usable"]
			],
			"action": ["sendNextPokemon"],
			"set": "hasNidoranM"
		},
		{
			"condition": ["all",
				["any",
					["activePokemon", "Nidoran M"],
					["activePokemon", "Nidorino"],
					["activePokemon", "Nidoking"]
				],
				["activeLevel", ">=", 14],
				["!isSet", "NidoranM ready for Viridian Jackson"]
			],
			"action": ["attack"],
			"set": "NidoranM ready for Viridian Jackson"
		},
		{
			"condition": ["all",
				["activeLevel", ">=", 65],
				["!isSet", "First pokemon does not need digglet cave"]
			],
			"action": ["attack"],
			"set": "First pokemon does not need digglet cave"
		},
		{
			"condition": ["all",
				["activeLevel", ">=", 43],
				["!isSet", "First pokemon ready for Surge"]
			],
			"action": ["attack"],
			"set": "First pokemon ready for Surge"
		},
		{
			"condition": ["all",
				["activeLevel", ">=", 38],
				["!isSet", "First pokemon ready for Misty"]
			],
			"action": ["attack"],
			"set": "First pokemon ready for Misty"
		},
		{
			"condition": ["all",
				["activeLevel", ">=", 28],
				["!isSet", "First pokemon ready for Mt.Moon"]
			],
			"action": ["attack"],
			"set": "First pokemon ready for Mt.Moon"
		},
		{
			"condition": ["all",
				["activeLevel", ">=", 21],
				["!isSet", "First pokemon ready for Moon Stone"]
			],
			"action": ["attack"],
			"set": "First pokemon ready for Moon Stone"
		},
		{
			"condition": ["all",
				["activeLevel", ">=", 16],
				["!isSet", "First pokemon ready for Brock"]
			],
			"action": ["attack"],
			"set": "First pokemon ready for Brock"
		},
		{
			"action": ["attack"]
		}
	],
	"switches": [
			["OAK", "but you can have one"],
			["OAK", "which pokemon do you want"],
			["MOM", "Remember that I love you"],
			["MOM", "glad that you dropped by"],
			["Viridian Jackson checked", "Maybe you can talk with him and try to negotiate the spot."],
			["Viridian Jackson defeated", "You will not take my spot!"],
			["Viridian Jackson defeated", "Sorry, the young boy there doesn't want to give his spot, I'm truly sorry..."],
			["Checked Viridian City to Route 2", "Why don't you go and check the school?"],
			["Viridian City to Route 2", "Well, now, I've had my coffee, and that's what I need to get going!"],
			["MtMoon go talk to fossil guy", "You should talk to someone before touching these."],
			["MtMoon talked to fossil guy", "Did you get the one you like?"],
			["Bill looking for book", "I am Bill, do you think you could do me a favor?"],
			["Bill found book", "Oh! Looks like Bill's research book is under his pillow."],
			["Bill found book", "There is nothing else here..."],
			["Bill has book", "Oh!! You found it!"],
			["Bill has book", "Have you enjoyed the Cruise yet?"],
			["Psychic Wade talked", "I wonder what that dude wants..."],
			["Psychic Wade explained", "You see, that was Lance, the Pokemon League Champion."],
			["Psychic Wade explained", "Please, hurry up and tell him that."],
			["Surge talked", "I am in the middle of something, you want to tell me something?"],
			["Psychic Wade congrated", "For your effort, I want to give you this, a token found from future Vermilion City!"],
			["Usher Dale talked", "Hello! Welcome aboard the S.S. Anne - the most upscale ship that is presently serviceable!"],
			["Usher Dale talked", "Enjoy your passengership on the S.S. Anne!"],
			["SSAnne Basement PC to check", "Welcome to S.S. Anne! Please book your personal information in our passenger registry."],
			["SSAnne Basement PC to check", "As apart of the guest-screening procedure, we will need you to register all applicable personal information at the PC, for ticket-identification purposes!"],
			["SSAnne Basement PC checked", "has been booked in the passenger registry of S.S. Anne!"],
			["SSAnne Doctor Neumann has Pecha Berry", "You have a Pecha Berry? Excellent!"],
			["SSAnne Doctor Neumann has Pecha Berry", "I was told the berry was delivered to him; thank you very much!"],
			["SSAnne Jenson needs Pecha Berry", "I was told the berry was delivered to him; thank you very much!"],
			["SSAnne Jenson needs Pecha Berry", "I did not know it was that grave, however!"],
			["SSAnne Jenson has Pecha Berry", "Excellent; let me take it!"],
			["SSAnne Jenson has Pecha Berry", "Explore the Ballroom for now; I already gave you an admissible ticket for it!"],
			["SSAnne Talked to Blissey", "Blissey wants to give something"],
			["SSAnne Security Officer Chris", "You should already know this area is off-limits!"],
			["SSAnne Captain", "I owe ye one..."],
			["SSAnne Jackson defeated", "Consider us off of the SS Anne now... With a goody-two-shoes scrub as my rommate, and the overall-pathetic pool of trainers, this ride will be a waste of time."],
			["Oak's Aide wants more pokemons", "Come back when you have; Professor Oak forwarded an item for me to give you when you do."]
	]
}
